comfygit_deploy/__init__.py
comfygit_deploy/cli.py
comfygit_deploy/config.py
comfygit_deploy/commands/__init__.py
comfygit_deploy/commands/custom.py
comfygit_deploy/commands/dev.py
comfygit_deploy/commands/instances.py
comfygit_deploy/commands/runpod.py
comfygit_deploy/commands/worker.py
comfygit_deploy/providers/__init__.py
comfygit_deploy/providers/custom.py
comfygit_deploy/providers/runpod.py
comfygit_deploy/startup/__init__.py
comfygit_deploy/startup/scripts.py
comfygit_deploy/worker/__init__.py
comfygit_deploy/worker/mdns.py
comfygit_deploy/worker/native_manager.py
comfygit_deploy/worker/server.py
comfygit_deploy/worker/state.py
comfygit_deploy-0.3.12.dist-info/METADATA
comfygit_deploy-0.3.12.dist-info/WHEEL
comfygit_deploy-0.3.12.dist-info/entry_points.txt
comfygit_deploy-0.3.12.dist-info/RECORD
