Metadata-Version: 2.4
Name: comfygit-deploy
Version: 0.3.12
Summary: ComfyGit Deploy - Remote deployment and worker management CLI
Requires-Python: >=3.10
Requires-Dist: aiohttp>=3.9.0
Requires-Dist: comfygit==0.3.12
Requires-Dist: zeroconf>=0.131.0
